[
  { "name": "An Giang", "id": 1, "case": 10, "color": 1 },
  { "name": "Bạc Liêu", "id": 2, "case": 10, "color": 0 },
  { "name": "Bắc Giang", "id": 3, "case": 10, "color": 0 },
  { "name": "Bắc Kạn", "id": 4, "case": 0, "color": 0 },
  { "name": "Bắc Ninh", "id": 5, "case": 10, "color": 0 },
  { "name": "Bến Tre", "id": 6, "case": 10, "color": 0 },
  { "name": "Bà Rịa - Vũng Tàu", "id": 7, "case":10, "color": 0 },
  { "name": "Bình Định", "id": 8, "case": 0, "color": 0 },
  { "name": "Bình Dương", "id": 9, "case": 0, "color": 0 },
  { "name": "Bình Phước", "id": 10, "case": 0, "color": 0 },
  { "name": "Bình Thuận", "id": 11, "case": 0, "color": 0 },
  { "name": "Cần Thơ", "id": 12, "case": 0, "color": 0 },
  { "name": "Cà Mau", "id": 13, "case": 0, "color": 0 },
  { "name": "Cao Bằng", "id": 14, "case": 0, "color": 0 },
  { "name": "Đắk Lắk", "id": 15, "case": 0, "color": 0 },
  { "name": "Đắk Nông", "id": 16, "case": 0, "color": 0 },
  { "name": "Đồng Nai", "id": 17, "case": 0, "color": 0 },
  { "name": "Đồng Tháp", "id": 18, "case": 0, "color": 0 },
  { "name": "Đà Nẵng", "id": 19, "case": 0, "color": 0 },
  { "name": "Điện Biên", "id": 20, "case": 0, "color": 0 },
  { "name": "Gia Lai", "id": 21, "case": 0, "color": 0 },
  { "name": "Hải Dương", "id": 22, "case": 0, "color": 0 },
  { "name": "Hải Phòng", "id": 23, "case": 0, "color": 0 },
  { "name": "Hậu Giang", "id": 24, "case": 0, "color": 0 },
  { "name": "Hồ Chí Minh", "id": 25, "case": 0, "color": 0 },
  { "name": "Hà Giang", "id": 26, "case": 0, "color": 0 },
  { "name": "Hà Nội", "id": 27, "case": 0, "color": 0 },
  { "name": "Hà Nam", "id": 28, "case": 0, "color": 0 },
  { "name": "Hà Tĩnh", "id": 29, "case": 0, "color": 0 },
  { "name": "Hoà Bình", "id": 30, "case": 0, "color": 0 },
  { "name": "Hưng Yên", "id": 31, "case": 0, "color": 0 },
  { "name": "Khánh Hòa", "id": 32, "case": 0, "color": 0 },
  { "name": "Kiên Giang", "id": 33, "case": 0, "color": 0 },
  { "name": "Kon Tum", "id": 34, "case": 0, "color": 0 },
  { "name": "Lạng Sơn", "id": 35, "case": 0, "color": 0 },
  { "name": "Lai Châu", "id": 36, "case": 0, "color": 0 },
  { "name": "Lâm Đồng", "id": 37, "case": 0, "color": 0 },
  { "name": "Lào Cai", "id": 38, "case": 0, "color": 0 },
  { "name": "Long An", "id": 39, "case": 0, "color": 0 },
  { "name": "Nam Định", "id": 40, "case": 0, "color": 0 },
  { "name": "Nghệ An", "id": 41, "case": 0, "color": 0 },
  { "name": "Ninh Bình", "id": 42, "case": 0, "color": 0 },
  { "name": "Ninh Thuận", "id": 43, "case": 0, "color": 0 },
  { "name": "Phú Thọ", "id": 44, "case": 0, "color": 0 },
  { "name": "Phú Yên", "id": 45, "case": 0, "color": 0 },
  { "name": "Quảng Bình", "id": 46, "case": 0, "color": 0 },
  { "name": "Quảng Nam", "id": 47, "case": 0, "color": 0 },
  { "name": "Quảng Ngãi", "id": 48, "case": 0, "color": 0 },
  { "name": "Quảng Ninh", "id": 49, "case": 0, "color": 0 },
  { "name": "Quảng Trị", "id": 50, "case": 0, "color": 0 },
  { "name": "Sóc Trăng", "id": 51, "case": 0, "color": 0 },
  { "name": "Sơn La", "id": 52, "case": 0, "color": 0 },
  { "name": "Tây Ninh", "id": 53, "case": 0, "color": 0 },
  { "name": "Thừa Thiên Huế", "id": 54, "case": 0, "color": 0 },
  { "name": "Thái Bình", "id": 55, "case": 0, "color": 0 },
  { "name": "Thái Nguyên", "id": 56, "case": 0, "color": 0 },
  { "name": "Thanh Hóa", "id": 57, "case": 0, "color": 0 },
  { "name": "Tiền Giang", "id": 58, "case": 0, "color": 0 },
  { "name": "Trà Vinh", "id": 59, "case": 0, "color": 0 },
  { "name": "Tuyên Quang", "id": 60, "case": 0, "color": 0 },
  { "name": "Vĩnh Long", "id": 61, "case": 0, "color": 0 },
  { "name": "Vĩnh Phúc", "id": 62, "case": 0, "color": 0 },
  { "name": "Yên Bái", "id": 63, "case": 0, "color": 0 }
]
